danielj/__init__.py
danielj/plot_utils.py
danielj/weather_forecast.py
danielj-1.0.0.dist-info/METADATA
danielj-1.0.0.dist-info/WHEEL
danielj-1.0.0.dist-info/top_level.txt
danielj-1.0.0.dist-info/RECORD
